adamspy/__init__.py
adamspy/adamspy.py
adamspy/acar/__init__.py
adamspy/acar/tire_testrig.py
adamspy/adripy/__init__.py
adamspy/adripy/constants.py
adamspy/adripy/database.py
adamspy/adripy/drillsim.py
adamspy/adripy/event.py
adamspy/adripy/hole.py
adamspy/adripy/solver_settings.py
adamspy/adripy/string.py
adamspy/adripy/tool.py
adamspy/adripy/utilities.py
adamspy/adripy/templates/template.cfg
adamspy/adripy/templates/template.evt
adamspy/adripy/templates/template.hol
adamspy/adripy/templates/template.ssf
adamspy/adripy/templates/template.sta
adamspy/adripy/templates/template_1.str
adamspy/adripy/templates/template_2.str
adamspy/adripy/templates/template_3.str
adamspy/adripy/templates/template_build.cmd
adamspy/aviewpy/__init__.py
adamspy/aviewpy/aviewpy.py
adamspy/postprocess/__init__.py
adamspy/postprocess/animation.py
adamspy/postprocess/exported.py
adamspy/postprocess/mode_tables.py
adamspy/postprocess/msg.py
adamspy/postprocess/ppt.py
adamspy/postprocess/xml.py
adamspy/postprocess/analysis/__init__.py
adamspy/postprocess/aview_scripts/edit_results.py
adamspy/postprocess/aview_scripts/get_lunar_results.py
adamspy/postprocess/aview_scripts/get_results.py
adamspy/waterfall/__init__.py
adamspy/waterfall/waterfall.py
adamspy-0.32.0.dist-info/LICENSE
adamspy-0.32.0.dist-info/METADATA
adamspy-0.32.0.dist-info/WHEEL
adamspy-0.32.0.dist-info/top_level.txt
adamspy-0.32.0.dist-info/RECORD
