Metadata-Version: 2.1
Name: adamspy
Version: 0.32.0
Summary: Python tools for working with Adams data
Home-page: https://github.com/bthornton191/adamspy
Author: Ben Thornton
Author-email: ben.thornton@mscsoftware.com
Classifier: Programming Language :: Python :: 3
Classifier: License :: OSI Approved :: MIT License
Classifier: Operating System :: Microsoft :: Windows
License-File: LICENSE
Requires-Dist: thornpy
Requires-Dist: numpy
Requires-Dist: pandas
Requires-Dist: Jinja2
Requires-Dist: dripy
Requires-Dist: scipy
Requires-Dist: matplotlib
